{
    "county": "hendry",
    "county_center_lat": 26.7533345,
    "county_center_long": -81.188653,
    "county_id": "HEN",
    "display_schedule": false,
    "display_wait_times": false,
    "election_date": "1880-01-01",
    "election_name": "No Current Election",
    "ev_end_date": "1880-01-01",
    "ev_start_date": "1880-01-01",
    "id": null,
    "locations": [
        {
            "uid": "GfeQvwjq",
            "webservices_id": "EV-1",
            "county_id": "HEN",
            "db_name": "vr6",
            "status_updated_at": "1900-01-01 00:00:00",
            "position": null,
            "hidden": false,
            "type": "Location",
            "images": [],
            "schedule": [],
            "prettySchedule": {},
            "evl_status_text": "Wait time not available",
            "evid_status_text": "Wait time not available",
            "color": "lightBlue",
            "evl_status": 5,
            "Id": "EV-1",
            "Type": "EarlyVoting",
            "Description": "EARLY VOTING LABELLE",
            "Address": "25 E Hickpochee Ave",
            "City": "LaBelle",
            "State": "FL",
            "Zip": "33935",
            "Latitude": 26.761783,
            "Longitude": -81.437166
        },
        {
            "uid": "ak6AiorF",
            "webservices_id": "EV-2",
            "county_id": "HEN",
            "db_name": "vr6",
            "status_updated_at": "1900-01-01 00:00:00",
            "position": null,
            "hidden": false,
            "type": "Location",
            "images": [],
            "schedule": [],
            "prettySchedule": {},
            "evl_status_text": "Wait time not available",
            "evid_status_text": "Wait time not available",
            "color": "lightBlue",
            "evl_status": 5,
            "Id": "EV-2",
            "Type": "EarlyVoting",
            "Description": "EARLY VOTING CLEWISTON",
            "Address": "1100 S Olympia",
            "City": "Clewiston",
            "State": "FL",
            "Zip": "33440",
            "Latitude": 26.744886,
            "Longitude": -80.94014
        }
    ],
    "registered_by": "1880-01-01",
    "status": "inactive",
    "usesVoteCenters": false,
    "timezone": "ET"
}
